mini_vk/__init__.py
mini_vk/api.py
mini_vk-0.1.3.dist-info/LICENSE
mini_vk-0.1.3.dist-info/METADATA
mini_vk-0.1.3.dist-info/WHEEL
mini_vk-0.1.3.dist-info/top_level.txt
mini_vk-0.1.3.dist-info/RECORD
