Metadata-Version: 2.1
Name: mini-vk
Version: 0.1.3
Summary: Small wrapper over the VK API
Home-page: https://github.com/SemenovAV/mini_vk
Author: SemenovAV
Author-email: 7.on.off@gmail.com
License: MIT
Platform: UNKNOWN
Classifier: Programming Language :: Python :: 3
Classifier: License :: OSI Approved :: MIT License
Classifier: Operating System :: OS Independent
Requires-Dist: requests
